{
	"name": "Paddle",
	"plugin-id": "Sprite",
	"sid": 9680992601730884,
	"isGlobal": false,
	"instanceVariables": [
		{
			"name": "peerid",
			"type": "string",
			"desc": "",
			"sid": 2040649148875527
		},
		{
			"name": "points",
			"type": "number",
			"desc": "",
			"sid": 7316904981992262
		}
	],
	"behaviorTypes": [
		{
			"behaviorId": "solid",
			"name": "Solid",
			"sid": 5452218702345515
		}
	],
	"effectTypes": [],
	"animations": {
		"items": [
			{
				"frames": [
					{
						"width": 300,
						"height": 300,
						"originX": 0.5,
						"originY": 0.5,
						"originalSource": "",
						"exportFormat": "lossless",
						"exportQuality": 0.8,
						"imageSpriteId": 2,
						"useCollisionPoly": true,
						"imagePoints": [
							{
								"name": "Imagepoint 1",
								"x": 1.04,
								"y": 0.513333
							}
						],
						"duration": 1
					}
				],
				"sid": 8757907285038088,
				"name": "Default",
				"isLooping": false,
				"isPingPong": false,
				"repeatCount": 1,
				"repeatTo": 0,
				"speed": 5
			}
		],
		"subfolders": []
	}
}